iapsync/__init__.py
iapsync/app/__init__.py
iapsync/app/main.py
iapsync/appstore/__init__.py
iapsync/appstore/appstore_pricing.py
iapsync/appstore/pricing-matrix.csv
iapsync/config/__init__.py
iapsync/config/config.py
iapsync/config/product-screenshot.png
iapsync/convert/__init__.py
iapsync/convert/convert.py
iapsync/defs/__init__.py
iapsync/defs/defs.py
iapsync/model/__init__.py
iapsync/model/product.py
iapsync/remote/__init__.py
iapsync/remote/fetch.py
iapsync/validate/__init__.py
iapsync/validate/validate.py
iapsync-1.0.7.dist-info/DESCRIPTION.rst
iapsync-1.0.7.dist-info/METADATA
iapsync-1.0.7.dist-info/RECORD
iapsync-1.0.7.dist-info/WHEEL
iapsync-1.0.7.dist-info/entry_points.txt
iapsync-1.0.7.dist-info/metadata.json
iapsync-1.0.7.dist-info/top_level.txt
