Metadata-Version: 2.0
Name: iapsync
Version: 1.0.7
Summary: script to update iap to itunesconnect
Home-page: https://github.com/bestofsong/iapsync
Author: bestofsong
Author-email: betterofsong@google.com
License: MIT
Keywords: ios in app purchase iap product update upload
Platform: UNKNOWN
Classifier: Development Status :: 3 - Alpha
Classifier: Intended Audience :: Developers
Classifier: Topic :: Software Development :: Build Tools
Classifier: License :: OSI Approved :: MIT License
Classifier: Programming Language :: Python :: 3.5
Classifier: Programming Language :: Python :: 3.6
Requires-Python: >=3
Requires-Dist: lxml
Requires-Dist: requests
